log_to/__init__.py
log_to/redis.py
tests/__init__.py
tests/test_handlers.py
python_send_logs_to-0.3.2.dist-info/LICENSE
python_send_logs_to-0.3.2.dist-info/METADATA
python_send_logs_to-0.3.2.dist-info/WHEEL
python_send_logs_to-0.3.2.dist-info/top_level.txt
python_send_logs_to-0.3.2.dist-info/RECORD
