Metadata-Version: 2.1
Name: python-send-logs-to
Version: 0.3.2
Summary: A Python logging handler that sends logs to Redis; later to be a collection of logging handlers.
Home-page: https://github.com/armandtvz/python-send-logs-to
Author: Armandt van Zyl
Author-email: armandtvz@gmail.com
License: MIT
Classifier: Development Status :: 4 - Beta
Classifier: Intended Audience :: Developers
Classifier: License :: OSI Approved :: MIT License
Classifier: Operating System :: OS Independent
Classifier: Programming Language :: Python
Classifier: Programming Language :: Python :: 3
Classifier: Programming Language :: Python :: 3.8
Classifier: Programming Language :: Python :: 3 :: Only
Requires-Python: >=3.8, <4
License-File: LICENSE
Requires-Dist: redis
